mandrake/__init__.py
mandrake/mm.py
mandrake/version.py
tests/__init__.py
tests/attribute.py
mandrake-0.0.2.dist-info/LICENCE
mandrake-0.0.2.dist-info/METADATA
mandrake-0.0.2.dist-info/WHEEL
mandrake-0.0.2.dist-info/top_level.txt
mandrake-0.0.2.dist-info/RECORD
