Metadata-Version: 2.1
Name: mandrake
Version: 0.0.2
Summary: All Magic Methods Implement. You can easyly to implement all magic methods or part of them
Home-page: https://github.com/estaleiroweb/mandrake
Author: Helbert Braga Fernandes
Author-email: helbertfernandes@gmail.com
License: MIT License
Keywords: magic methods class
Platform: UNKNOWN
Classifier: Development Status :: 5 - Production/Stable
Classifier: License :: OSI Approved :: MIT License
Classifier: Programming Language :: Python :: 2
Classifier: Programming Language :: Python :: 3
Classifier: Operating System :: OS Independent
Requires-Python: >=2.0
License-File: LICENCE
